{
  "scriptId": "14",
  "url": "deno:ext/web/02_event.js",
  "functions": [
    {
      "functionName": "getDispatched",
      "ranges": [
        {
          "startOffset": 1223,
          "endOffset": 1298,
          "count": 1
        }
      ],
      "isBlockCoverage": true
    },
    {
      "functionName": "getPath",
      "ranges": [
        {
          "startOffset": 1302,
          "endOffset": 1362,
          "count": 3
        },
        {
          "startOffset": 1352,
          "endOffset": 1357,
          "count": 0
        }
      ],
      "isBlockCoverage": true
    },
    {
      "functionName": "getStopImmediatePropagation",
      "ranges": [
        {
          "startOffset": 1366,
          "endOffset": 1473,
          "count": 1
        }
      ],
      "isBlockCoverage": true
    },
    {
      "functionName": "setCurrentTarget",
      "ranges": [
        {
          "startOffset": 1477,
          "endOffset": 1581,
          "count": 2
        }
      ],
      "isBlockCoverage": true
    },
    {
      "functionName": "setDispatched",
      "ranges": [
        {
          "startOffset": 1661,
          "endOffset": 1735,
          "count": 2
        }
      ],
      "isBlockCoverage": true
    },
    {
      "functionName": "setEventPhase",
      "ranges": [
        {
          "startOffset": 1739,
          "endOffset": 1824,
          "count": 3
        }
      ],
      "isBlockCoverage": true
    },
    {
      "functionName": "setInPassiveListener",
      "ranges": [
        {
          "startOffset": 1828,
          "endOffset": 1916,
          "count": 1
        }
      ],
      "isBlockCoverage": true
    },
    {
      "functionName": "setPath",
      "ranges": [
        {
          "startOffset": 1920,
          "endOffset": 1982,
          "count": 1
        }
      ],
      "isBlockCoverage": true
    },
    {
      "functionName": "setRelatedTarget",
      "ranges": [
        {
          "startOffset": 1986,
          "endOffset": 2090,
          "count": 1
        }
      ],
      "isBlockCoverage": true
    },
    {
      "functionName": "setTarget",
      "ranges": [
        {
          "startOffset": 2094,
          "endOffset": 2171,
          "count": 2
        }
      ],
      "isBlockCoverage": true
    },
    {
      "functionName": "setStopImmediatePropagation",
      "ranges": [
        {
          "startOffset": 2175,
          "endOffset": 2294,
          "count": 1
        }
      ],
      "isBlockCoverage": true
    },
    {
      "functionName": "hasRelatedTarget",
      "ranges": [
        {
          "startOffset": 2342,
          "endOffset": 2426,
          "count": 1
        }
      ],
      "isBlockCoverage": true
    },
    {
      "functionName": "<instance_members_initializer>",
      "ranges": [
        {
          "startOffset": 3402,
          "endOffset": 3635,
          "count": 2
        }
      ],
      "isBlockCoverage": false
    },
    {
      "functionName": "Event",
      "ranges": [
        {
          "startOffset": 3642,
          "endOffset": 4378,
          "count": 2
        }
      ],
      "isBlockCoverage": true
    },
    {
      "functionName": "get type",
      "ranges": [
        {
          "startOffset": 4614,
          "endOffset": 4669,
          "count": 4
        }
      ],
      "isBlockCoverage": true
    },
    {
      "functionName": "get currentTarget",
      "ranges": [
        {
          "startOffset": 4855,
          "endOffset": 4928,
          "count": 1
        }
      ],
      "isBlockCoverage": true
    },
    {
      "functionName": "get NONE",
      "ranges": [
        {
          "startOffset": 8013,
          "endOffset": 8047,
          "count": 4
        }
      ],
      "isBlockCoverage": true
    },
    {
      "functionName": "get CAPTURING_PHASE",
      "ranges": [
        {
          "startOffset": 8060,
          "endOffset": 8105,
          "count": 2
        }
      ],
      "isBlockCoverage": true
    },
    {
      "functionName": "get AT_TARGET",
      "ranges": [
        {
          "startOffset": 8118,
          "endOffset": 8157,
          "count": 2
        }
      ],
      "isBlockCoverage": true
    },
    {
      "functionName": "get BUBBLING_PHASE",
      "ranges": [
        {
          "startOffset": 8170,
          "endOffset": 8214,
          "count": 2
        }
      ],
      "isBlockCoverage": true
    },
    {
      "functionName": "get eventPhase",
      "ranges": [
        {
          "startOffset": 8220,
          "endOffset": 8287,
          "count": 5
        }
      ],
      "isBlockCoverage": true
    },
    {
      "functionName": "get cancelBubble",
      "ranges": [
        {
          "startOffset": 8365,
          "endOffset": 8432,
          "count": 1
        }
      ],
      "isBlockCoverage": true
    },
    {
      "functionName": "set cancelBubble",
      "ranges": [
        {
          "startOffset": 8438,
          "endOffset": 8538,
          "count": 1
        }
      ],
      "isBlockCoverage": true
    },
    {
      "functionName": "get defaultPrevented",
      "ranges": [
        {
          "startOffset": 9153,
          "endOffset": 9217,
          "count": 1
        }
      ],
      "isBlockCoverage": true
    },
    {
      "functionName": "getParent",
      "ranges": [
        {
          "startOffset": 10282,
          "endOffset": 10383,
          "count": 1
        },
        {
          "startOffset": 10347,
          "endOffset": 10371,
          "count": 0
        }
      ],
      "isBlockCoverage": true
    },
    {
      "functionName": "isNode",
      "ranges": [
        {
          "startOffset": 10523,
          "endOffset": 10628,
          "count": 7
        },
        {
          "startOffset": 10594,
          "endOffset": 10622,
          "count": 5
        }
      ],
      "isBlockCoverage": true
    },
    {
      "functionName": "isShadowRoot",
      "ranges": [
        {
          "startOffset": 11021,
          "endOffset": 11222,
          "count": 1
        },
        {
          "startOffset": 11118,
          "endOffset": 11173,
          "count": 0
        },
        {
          "startOffset": 11174,
          "endOffset": 11210,
          "count": 0
        }
      ],
      "isBlockCoverage": true
    },
    {
      "functionName": "isSlotable",
      "ranges": [
        {
          "startOffset": 11226,
          "endOffset": 11338,
          "count": 1
        },
        {
          "startOffset": 11303,
          "endOffset": 11332,
          "count": 0
        }
      ],
      "isBlockCoverage": true
    },
    {
      "functionName": "appendToEventPath",
      "ranges": [
        {
          "startOffset": 11489,
          "endOffset": 12033,
          "count": 1
        },
        {
          "startOffset": 11673,
          "endOffset": 11705,
          "count": 0
        },
        {
          "startOffset": 11757,
          "endOffset": 11794,
          "count": 0
        }
      ],
      "isBlockCoverage": true
    },
    {
      "functionName": "dispatch",
      "ranges": [
        {
          "startOffset": 12037,
          "endOffset": 16473,
          "count": 1
        },
        {
          "startOffset": 12330,
          "endOffset": 12355,
          "count": 0
        },
        {
          "startOffset": 12474,
          "endOffset": 12510,
          "count": 0
        },
        {
          "startOffset": 12793,
          "endOffset": 12832,
          "count": 0
        },
        {
          "startOffset": 12834,
          "endOffset": 12882,
          "count": 0
        },
        {
          "startOffset": 12964,
          "endOffset": 12994,
          "count": 0
        },
        {
          "startOffset": 13003,
          "endOffset": 13015,
          "count": 0
        },
        {
          "startOffset": 13183,
          "endOffset": 14512,
          "count": 0
        },
        {
          "startOffset": 14921,
          "endOffset": 14979,
          "count": 0
        },
        {
          "startOffset": 15033,
          "endOffset": 15100,
          "count": 0
        },
        {
          "startOffset": 15278,
          "endOffset": 15339,
          "count": 0
        },
        {
          "startOffset": 15526,
          "endOffset": 15601,
          "count": 0
        },
        {
          "startOffset": 15673,
          "endOffset": 15705,
          "count": 0
        },
        {
          "startOffset": 16104,
          "endOffset": 16186,
          "count": 0
        }
      ],
      "isBlockCoverage": true
    },
    {
      "functionName": "innerInvokeEventListeners",
      "ranges": [
        {
          "startOffset": 16650,
          "endOffset": 18574,
          "count": 1
        },
        {
          "startOffset": 16837,
          "endOffset": 16864,
          "count": 0
        },
        {
          "startOffset": 17198,
          "endOffset": 17290,
          "count": 0
        },
        {
          "startOffset": 17592,
          "endOffset": 17619,
          "count": 0
        },
        {
          "startOffset": 17709,
          "endOffset": 17720,
          "count": 0
        },
        {
          "startOffset": 17780,
          "endOffset": 17790,
          "count": 0
        },
        {
          "startOffset": 17800,
          "endOffset": 17827,
          "count": 0
        },
        {
          "startOffset": 17845,
          "endOffset": 18007,
          "count": 0
        },
        {
          "startOffset": 18028,
          "endOffset": 18084,
          "count": 0
        },
        {
          "startOffset": 18135,
          "endOffset": 18273,
          "count": 0
        },
        {
          "startOffset": 18514,
          "endOffset": 18545,
          "count": 0
        }
      ],
      "isBlockCoverage": true
    },
    {
      "functionName": "invokeEventListeners",
      "ranges": [
        {
          "startOffset": 18730,
          "endOffset": 19264,
          "count": 1
        },
        {
          "startOffset": 19124,
          "endOffset": 19145,
          "count": 0
        }
      ],
      "isBlockCoverage": true
    },
    {
      "functionName": "retarget",
      "ranges": [
        {
          "startOffset": 19902,
          "endOffset": 20251,
          "count": 1
        },
        {
          "startOffset": 19996,
          "endOffset": 20241,
          "count": 0
        }
      ],
      "isBlockCoverage": true
    },
    {
      "functionName": "getListeners",
      "ranges": [
        {
          "startOffset": 20830,
          "endOffset": 20939,
          "count": 1
        },
        {
          "startOffset": 20929,
          "endOffset": 20934,
          "count": 0
        }
      ],
      "isBlockCoverage": true
    },
    {
      "functionName": "dispatchEvent",
      "ranges": [
        {
          "startOffset": 24054,
          "endOffset": 24723,
          "count": 2
        },
        {
          "startOffset": 24235,
          "endOffset": 24248,
          "count": 0
        },
        {
          "startOffset": 24367,
          "endOffset": 24463,
          "count": 1
        },
        {
          "startOffset": 24463,
          "endOffset": 24549,
          "count": 0
        },
        {
          "startOffset": 24549,
          "endOffset": 24594,
          "count": 1
        },
        {
          "startOffset": 24594,
          "endOffset": 24680,
          "count": 0
        },
        {
          "startOffset": 24680,
          "endOffset": 24722,
          "count": 1
        }
      ],
      "isBlockCoverage": true
    }
  ]
}
